curation_magic/__init__.py
curation_magic/_nbdev.py
curation_magic/curator.py
curation_magic/cutor.py
curation_magic-1.0.0.dist-info/LICENSE
curation_magic-1.0.0.dist-info/METADATA
curation_magic-1.0.0.dist-info/WHEEL
curation_magic-1.0.0.dist-info/entry_points.txt
curation_magic-1.0.0.dist-info/top_level.txt
curation_magic-1.0.0.dist-info/RECORD
