Metadata-Version: 2.1
Name: curation-magic
Version: 1.0.0
Summary: "A tool to curate a test set from a set of constraints"
Home-page: https://github.com/jonilaserson/curation_magic
Author: Jonathan Laserson
Author-email: jonil@zebra-med.com
License: Apache Software License 2.0
Keywords: LP curation
Platform: UNKNOWN
Classifier: Development Status :: 3 - Alpha
Classifier: Intended Audience :: Developers
Classifier: License :: OSI Approved :: Apache Software License
Classifier: Natural Language :: English
Classifier: Programming Language :: Python :: 3.6
Classifier: Programming Language :: Python :: 3.7
Classifier: Programming Language :: Python :: 3.8
Requires-Python: >=3.6
